granite_tsfm-0.3.3.dist-info/licenses/LICENSE
tsfm_public/__init__.py
tsfm_public/_version.py
tsfm_public/version.py
tsfm_public/models/__init__.py
tsfm_public/models/flowstate/__init__.py
tsfm_public/models/flowstate/configuration_flowstate.py
tsfm_public/models/flowstate/modeling_flowstate.py
tsfm_public/models/flowstate/utils/utils.py
tsfm_public/models/flowstate/utils/figs/FlowState.png
tsfm_public/models/flowstate/utils/figs/flowstate_performance.png
tsfm_public/models/tinytimemixer/README.md
tsfm_public/models/tinytimemixer/__init__.py
tsfm_public/models/tinytimemixer/configuration_tinytimemixer.py
tsfm_public/models/tinytimemixer/modeling_tinytimemixer.py
tsfm_public/models/tinytimemixer/utils/__init__.py
tsfm_public/models/tinytimemixer/utils/ad_helpers.py
tsfm_public/models/tinytimemixer/utils/ttm_args.py
tsfm_public/models/tinytimemixer/utils/ttm_image.webp
tsfm_public/models/tspulse/__init__.py
tsfm_public/models/tspulse/configuration_tspulse.py
tsfm_public/models/tspulse/modeling_tspulse.py
tsfm_public/models/tspulse/utils/__init__.py
tsfm_public/models/tspulse/utils/ad_helpers.py
tsfm_public/models/tspulse/utils/helpers.py
tsfm_public/resources/__init__.py
tsfm_public/resources/data_config/__init__.py
tsfm_public/resources/data_config/electricity.yaml
tsfm_public/resources/data_config/etth1.yaml
tsfm_public/resources/data_config/etth2.yaml
tsfm_public/resources/data_config/ettm1.yaml
tsfm_public/resources/data_config/ettm2.yaml
tsfm_public/resources/data_config/exchange.yaml
tsfm_public/resources/data_config/solar.yaml
tsfm_public/resources/data_config/traffic.yaml
tsfm_public/resources/data_config/weather.yaml
tsfm_public/resources/data_config/zafnoo.yaml
tsfm_public/resources/model_paths_config/__init__.py
tsfm_public/resources/model_paths_config/ttm.yaml
tsfm_public/toolkit/__init__.py
tsfm_public/toolkit/ad_helpers.py
tsfm_public/toolkit/callbacks.py
tsfm_public/toolkit/conformal.py
tsfm_public/toolkit/data_handling.py
tsfm_public/toolkit/dataset.py
tsfm_public/toolkit/get_model.py
granite_tsfm-0.3.3.dist-info/METADATA
granite_tsfm-0.3.3.dist-info/WHEEL
granite_tsfm-0.3.3.dist-info/top_level.txt
granite_tsfm-0.3.3.dist-info/RECORD
