Metadata-Version: 2.4
Name: granite-tsfm
Version: 0.3.3
Summary: Public notebooks and utilities for TSFM
Author: IBM
License:                                  Apache License
Classifier: Development Status :: 4 - Beta
Classifier: License :: OSI Approved :: Apache Software License
Requires-Python: <3.14,>=3.9
License-File: LICENSE
Requires-Dist: pandas>=2.2.0
Requires-Dist: scikit-learn
Requires-Dist: transformers[torch]==4.56.0
Requires-Dist: datasets
Requires-Dist: deprecated
Requires-Dist: urllib3>=1.26.19
Requires-Dist: numpy<3
Requires-Dist: torch<2.9
Requires-Dist: scikit-learn<1.8
Provides-Extra: all
Requires-Dist: granite-tsfm[dev,notebooks,testing]; extra == "all"
Provides-Extra: notebooks
Requires-Dist: jupyter; extra == "notebooks"
Requires-Dist: matplotlib; extra == "notebooks"
Requires-Dist: datasets; extra == "notebooks"
Requires-Dist: ipywidgets; extra == "notebooks"
Requires-Dist: plotly; extra == "notebooks"
Requires-Dist: kaleido; extra == "notebooks"
Requires-Dist: tensorboard; extra == "notebooks"
Provides-Extra: testing
Requires-Dist: pytest; extra == "testing"
Requires-Dist: pytest-coverage; extra == "testing"
Requires-Dist: granite-tsfm[notebooks]; extra == "testing"
Requires-Dist: parameterized; extra == "testing"
Provides-Extra: dev
Requires-Dist: granite-tsfm[testing]; extra == "dev"
Requires-Dist: ruff==0.5.7; extra == "dev"
Provides-Extra: ogv
Requires-Dist: datasets; extra == "ogv"
Requires-Dist: plotly; extra == "ogv"
Requires-Dist: kaleido; extra == "ogv"
Provides-Extra: demos
Requires-Dist: granite-tsfm[notebooks]; extra == "demos"
Requires-Dist: streamlit; extra == "demos"
Requires-Dist: altair<5; extra == "demos"
Requires-Dist: plotly; extra == "demos"
Requires-Dist: streamlit-aggrid; extra == "demos"
Requires-Dist: kaleido; extra == "demos"
Requires-Dist: toml; extra == "demos"
Dynamic: license-file
